lilyweight/__init__.py
lilyweight/constants.py
lilyweight/main.py
lilyweight/utils.py
lilyweight/calcs/__init__.py
lilyweight/calcs/dungeon_comp_weight.py
lilyweight/calcs/dungeon_xp_weight.py
lilyweight/calcs/skill_weight.py
lilyweight/calcs/slayer_weight.py
lilyweight-0.0.5.dist-info/LICENSE
lilyweight-0.0.5.dist-info/METADATA
lilyweight-0.0.5.dist-info/WHEEL
lilyweight-0.0.5.dist-info/top_level.txt
lilyweight-0.0.5.dist-info/RECORD
