Metadata-Version: 2.1
Name: lilyweight
Version: 0.0.5
Summary: Hypixel SkyBlock Weight Calculator.
Home-page: UNKNOWN
Author: timnoot
Author-email: <hypixelskyhub@gmail.com>
License: UNKNOWN
Keywords: python,hypixel,skyblock,lily weight,weight,lappysheep,lilly
Platform: UNKNOWN
Classifier: Development Status :: 5 - Production/Stable
Classifier: Intended Audience :: Developers
Classifier: Operating System :: OS Independent
Classifier: License :: OSI Approved :: MIT License
Classifier: Programming Language :: Python :: 3
License-File: LICENSE
Requires-Dist: aiohttp
